./.gitignore
./PKG-INFO
./README.md
./pyproject.toml
./assets/observe.png
./hiagent_observe/__init__.py
./hiagent_observe/client.py
./hiagent_observe/helper.py
./hiagent_observe/semconv/__init__.py
hiagent_observe-2.0.2.dist-info/METADATA
hiagent_observe-2.0.2.dist-info/WHEEL
hiagent_observe-2.0.2.dist-info/RECORD
